odoo/addons/web_widget_image_url/README.rst
odoo/addons/web_widget_image_url/__init__.py
odoo/addons/web_widget_image_url/__manifest__.py
odoo/addons/web_widget_image_url/i18n/ca.po
odoo/addons/web_widget_image_url/i18n/es.po
odoo/addons/web_widget_image_url/i18n/pt_BR.po
odoo/addons/web_widget_image_url/i18n/tr.po
odoo/addons/web_widget_image_url/i18n/web_widget_image_url.pot
odoo/addons/web_widget_image_url/i18n/zh_CN.po
odoo/addons/web_widget_image_url/readme/CONTRIBUTORS.rst
odoo/addons/web_widget_image_url/readme/DESCRIPTION.rst
odoo/addons/web_widget_image_url/readme/USAGE.rst
odoo/addons/web_widget_image_url/static/description/icon.png
odoo/addons/web_widget_image_url/static/description/image.png
odoo/addons/web_widget_image_url/static/description/index.html
odoo/addons/web_widget_image_url/static/src/js/web_widget_image_url.js
odoo/addons/web_widget_image_url/static/src/xml/web_widget_image_url.xml
odoo/addons/web_widget_image_url/views/web_widget_image_url.xml
odoo12_addon_web_widget_image_url-12.0.1.1.0.dist-info/METADATA
odoo12_addon_web_widget_image_url-12.0.1.1.0.dist-info/WHEEL
odoo12_addon_web_widget_image_url-12.0.1.1.0.dist-info/top_level.txt
odoo12_addon_web_widget_image_url-12.0.1.1.0.dist-info/RECORD
